{
  "input_path": "/home/suramya/HHP-Prediction/OHC/output/ml_collocation/data/argo_rtofs_collocated_2024_2025.parquet",
  "output_path": "/home/suramya/HHP-Prediction/OHC/output/ml_collocation/data/argo_rtofs_collocated_2024_2025_neighborhood.parquet",
  "rows_total": 41347,
  "dates_total": 90,
  "dates_with_fields": 90,
  "scales_cells": {
    "halfdeg": 6,
    "1deg": 12,
    "2deg": 25
  },
  "elapsed_s": 73.1,
  "feature_availability": {
    "model_tchp_local_mean_halfdeg": 13538,
    "model_tchp_local_std_halfdeg": 13538,
    "model_tchp_local_mean_1deg": 13710,
    "model_tchp_local_std_1deg": 13710,
    "model_tchp_local_mean_2deg": 13981,
    "model_tchp_local_std_2deg": 13981,
    "model_tchp_grad_mag_per_100km": 12894,
    "model_tchp_anom_from_1deg_mean": 13101,
    "model_d26_local_mean_halfdeg": 13538,
    "model_d26_local_std_halfdeg": 13538,
    "model_d26_local_mean_1deg": 13710,
    "model_d26_local_std_1deg": 13710,
    "model_d26_local_mean_2deg": 13981,
    "model_d26_local_std_2deg": 13981,
    "model_d26_grad_mag_per_100km": 12894,
    "model_d26_anom_from_1deg_mean": 13101,
    "model_sst_local_mean_halfdeg": 41315,
    "model_sst_local_std_halfdeg": 41315,
    "model_sst_local_mean_1deg": 41346,
    "model_sst_local_std_1deg": 41346,
    "model_sst_local_mean_2deg": 41346,
    "model_sst_local_std_2deg": 41346,
    "model_sst_grad_mag_per_100km": 41261,
    "model_sst_anom_from_1deg_mean": 41298
  }
}